py_sync_dotenv/__init__.py
py_sync_dotenv/cli.py
py_sync_dotenv/py_sync_dotenv.py
py_sync_dotenv-0.1.3.dist-info/AUTHORS.rst
py_sync_dotenv-0.1.3.dist-info/LICENSE
py_sync_dotenv-0.1.3.dist-info/METADATA
py_sync_dotenv-0.1.3.dist-info/WHEEL
py_sync_dotenv-0.1.3.dist-info/entry_points.txt
py_sync_dotenv-0.1.3.dist-info/top_level.txt
py_sync_dotenv-0.1.3.dist-info/RECORD
