Metadata-Version: 2.1
Name: py-sync-dotenv
Version: 0.1.3
Summary: Python Sync Dotenv is a Python package for synchronizing .env files  across projects.
Home-page: https://github.com/IamAbbey/py_sync_dotenv
Author: Sotunde Abiodun Oladimeji
Author-email: sotundeabiodun00@gmail.com
License: MIT license
Keywords: py_sync_dotenv
Classifier: Development Status :: 2 - Pre-Alpha
Classifier: Intended Audience :: Developers
Classifier: License :: OSI Approved :: MIT License
Classifier: Natural Language :: English
Classifier: Programming Language :: Python :: 3.8
Requires-Python: >=3.8
License-File: LICENSE
License-File: AUTHORS.rst
